odoo10_addon_invader_payment_sips-10.0.2.0.1-py3.8-nspkg.pth
odoo/addons/invader_payment_sips/README.rst
odoo/addons/invader_payment_sips/__init__.py
odoo/addons/invader_payment_sips/__manifest__.py
odoo/addons/invader_payment_sips/demo/payment_demo.xml
odoo/addons/invader_payment_sips/models/__init__.py
odoo/addons/invader_payment_sips/models/payment_acquirer.py
odoo/addons/invader_payment_sips/models/payment_transaction.py
odoo/addons/invader_payment_sips/readme/CONTRIBUTORS.rst
odoo/addons/invader_payment_sips/readme/DESCRIPTION.rst
odoo/addons/invader_payment_sips/services/__init__.py
odoo/addons/invader_payment_sips/services/payment_sips.py
odoo/addons/invader_payment_sips/static/description/index.html
odoo/addons/invader_payment_sips/views/payment_acquirer.xml
odoo10_addon_invader_payment_sips-10.0.2.0.1.dist-info/METADATA
odoo10_addon_invader_payment_sips-10.0.2.0.1.dist-info/WHEEL
odoo10_addon_invader_payment_sips-10.0.2.0.1.dist-info/namespace_packages.txt
odoo10_addon_invader_payment_sips-10.0.2.0.1.dist-info/top_level.txt
odoo10_addon_invader_payment_sips-10.0.2.0.1.dist-info/RECORD
