Metadata-Version: 2.1
Name: odoo10-addon-invader-payment-sips
Version: 10.0.2.0.1
Summary: REST Services for Worldline SIPS Payments (base module)
Home-page: https://github.com/shopinvader/odoo-shopinvader-payment
Author: ACSONE SA/NV
License: AGPL-3
Platform: UNKNOWN
Classifier: Programming Language :: Python
Classifier: Framework :: Odoo
Classifier: License :: OSI Approved :: GNU Affero General Public License v3
Requires-Python: ~=2.7
Requires-Dist: cerberus
Requires-Dist: odoo10-addon-base-rest
Requires-Dist: odoo10-addon-invader-payment
Requires-Dist: odoo (<10.1dev,>=10.0)
